{
  "Theme": {
    "name": "Sber",
    "stylesMap": {
      "accentActiveColor": "#f48923",
      "accentBorderColor": "#fd9827",
      "accentDefaultColor": "#fd9827",
      "accentHoverColor": "#f89025",
      "accentTextColor": "#fd9827",
      "blockBackground": "#ffffff",
      "bodyBackground": "#ffffff",
      "cellHover": "#f3f5f9",
      "disabledColor": "#e5e5e5",
      "iconDefaultColor": "#9a9ca3",
      "iconHoverColor": "#585c67",
      "inputBackground": "#ffffff",
      "inputBorder": "#d6d8dd",
      "inputBorderActive": "#005e7f",
      "inputBorderHover": "#cbcdd3",
      "labelsTextColor": "#9a9ca3",
      "linkColor": "#155696",
      "mainTextColor": "#0c0c0c",
      "mutedTextColor": "#9a9ca3",
      "negativeActiveColor": "#e03122",
      "negativeBorderColor": "#e73626",
      "negativeDefaultColor": "#e73626",
      "negativeHoverColor": "#e33324",
      "onAccentActiveColor": "#ffffff",
      "onAccentDefaultColor": "#ffffff",
      "onAccentHoverColor": "#ffffff",
      "onNegativeActiveColor": "#ffffff",
      "onNegativeDefaultColor": "#ffffff",
      "onNegativeHoverColor": "#ffffff",
      "onPrimaryActiveColor": "#ffffff",
      "onPrimaryDefaultColor": "#ffffff",
      "onPrimaryHoverColor": "#ffffff",
      "onSecondaryActiveColor": "#ffffff",
      "onSecondaryDefaultColor": "#0c0c0c",
      "onSecondaryHoverColor": "#ffffff",
      "primaryActiveColor": "#005e7f",
      "primaryBorderColor": "#107f8c",
      "primaryDefaultColor": "#107f8c",
      "primaryHoverColor": "#21a19a",
      "primaryTextColor": "#107f8c",
      "secondaryActiveColor": "#0c0c0c",
      "secondaryBorderColor": "#9a9ca3",
      "secondaryDefaultColor": "#ffffff",
      "secondaryHoverColor": "#0c0c0c",
      "secondaryText": "#585c67",
      "separatorsColor": "#d6d8dd",
      "statusError": "#e73626",
      "statusSuccess": "#2fbb17",
      "statusWarning": "#fd9827"
    },
    "mainPalette": {
      "primary100": "#e8f2f3",
      "primary200": "#c6dfe2",
      "primary300": "#a4ccd1",
      "primary400": "#82b9bf",
      "primary500": "#5fa5ae",
      "primary600": "#3d929c",
      "primary700": "#107f8c",
      "primary800": "#21a19a",
      "primary900": "#005e7f",
      "danger100": "#fdebe9",
      "danger200": "#f9cdc9",
      "danger300": "#f5afa8",
      "danger400": "#f29088",
      "danger500": "#ee7267",
      "danger600": "#eb5447",
      "danger700": "#e73626",
      "danger800": "#e33324",
      "danger900": "#e03122",
      "gray0": "#ffffff",
      "gray100": "#f3f5f9",
      "gray200": "#ebeff4",
      "gray300": "#e5e5e5",
      "gray400": "#d6d8dd",
      "gray450": "#cbcdd3",
      "gray500": "#9a9ca3",
      "gray600": "#585c67",
      "gray900": "#0c0c0c",
      "link100": "#e8eef5",
      "link200": "#c5d5e5",
      "link300": "#a1bbd5",
      "link400": "#7ea2c5",
      "link500": "#5b89b6",
      "link600": "#386fa6",
      "link700": "#155696",
      "link800": "#1c528f",
      "link900": "#234d87",
      "accent100": "#fff5e9",
      "accent200": "#ffe5c9",
      "accent300": "#fed6a9",
      "accent400": "#fec688",
      "accent500": "#feb768",
      "accent600": "#fda747",
      "accent700": "#fd9827",
      "accent800": "#f89025",
      "accent900": "#f48923",
      "success100": "#eaf8e8",
      "success200": "#cbeec5",
      "success300": "#ace4a2",
      "success400": "#8dda7f",
      "success500": "#6dcf5d",
      "success600": "#4ec53a",
      "success700": "#2fbb17",
      "success800": "#2fbb17",
      "success900": "#3aa815"
    }
  }
}
